[
  {
    "text": "The only thing we have to fear is fear itself.",
    "speaker": "Franklin D. Roosevelt",
    "id": "1"
  },
  {
    "text": "I have a dream that one day this nation will rise up and live out the true meaning of its creed: \"We hold these truths to be self-evident, that all men are created equal.\"",
    "speaker": "Martin Luther King Jr.",
    "id": "2"
  },
  {
    "text": "The only way to do great work is to love what you do.",
    "speaker": "Steve Jobs",
    "id": "3"
  },
  {
    "text": "In three words I can sum up everything I've learned about life: it goes on.",
    "speaker": "Robert Frost",
    "id": "4"
  },
  {
    "text": "The only person you are destined to become is the person you decide to be.",
    "speaker": "Ralph Waldo Emerson",
    "id": "5"
  },
  {
    "text": "It does not matter how slowly you go as long as you do not stop.",
    "speaker": "Confucius",
    "id": "6"
  },
  {
    "text": "The future belongs to those who believe in the beauty of their dreams.",
    "speaker": "Eleanor Roosevelt",
    "id": "7"
  },
  {
    "text": "The only thing necessary for the triumph of evil is for good men to do nothing.",
    "speaker": "Edmund Burke",
    "id": "8"
  },
  {
    "text": "The best way to find yourself is to lose yourself in the service of others.",
    "speaker": "Mahatma Gandhi",
    "id": "9"
  },
  {
    "text": "The only limit to our realization of tomorrow will be our doubts of today.",
    "speaker": "Franklin D. Roosevelt",
    "id": "10"
  },
  {
    "text": "The measure of intelligence is the ability to change.",
    "speaker": "Albert Einstein",
    "id": "11"
  },
  {
    "text": "The only thing constant in life is change.",
    "speaker": "Heraclitus",
    "id": "12"
  },
  {
    "text": "The greatest glory in living lies not in never falling, but in rising every time we fall.",
    "speaker": "Nelson Mandela",
    "id": "13"
  },
  {
    "text": "The only true wisdom is in knowing you know nothing.",
    "speaker": "Socrates",
    "id": "14"
  },
  {
    "text": "The future belongs to those who prepare for it today.",
    "speaker": "Malcolm X",
    "id": "15"
  },
  {
    "text": "The only way to do great work is to love what you do.",
    "speaker": "Steve Jobs",
    "id": "16"
  },
  {
    "text": "The only thing we have to fear is fear itself.",
    "speaker": "Franklin D. Roosevelt",
    "id": "17"
  },
  {
    "text": "The only person you are destined to become is the person you decide to be.",
    "speaker": "Ralph Waldo Emerson",
    "id": "18"
  },
  {
    "text": "The only limit to our realization of tomorrow will be our doubts of today.",
    "speaker": "Franklin D. Roosevelt",
    "id": "19"
  },
  {
    "text": "The only thing constant in life is change.",
    "speaker": "Heraclitus",
    "id": "20"
  },
  {
    "text": "The greatest glory in living lies not in never falling, but in rising every time we fall.",
    "speaker": "Nelson Mandela",
    "id": "21"
  },
  {
    "text": "The only true wisdom is in knowing you know nothing.",
    "speaker": "Socrates",
    "id": "22"
  },
  {
    "text": "The future belongs to those who prepare for it today.",
    "speaker": "Malcolm X",
    "id": "23"
  },
  {
    "text": "The only thing necessary for the triumph of evil is for good men to do nothing.",
    "speaker": "Edmund Burke",
    "id": "24"
  },
  {
    "text": "The best way to find yourself is to lose yourself in the service of others.",
    "speaker": "Mahatma Gandhi",
    "id": "25"
  },
  {
    "text": "The measure of intelligence is the ability to change.",
    "speaker": "Albert Einstein",
    "id": "26"
  },
  {
    "text": "The future belongs to those who believe in the beauty of their dreams.",
    "speaker": "Eleanor Roosevelt",
    "id": "27"
  },
  {
    "text": "It does not matter how slowly you go as long as you do not stop.",
    "speaker": "Confucius",
    "id": "28"
  },
  {
    "text": "In three words I can sum up everything I've learned about life: it goes on.",
    "speaker": "Robert Frost",
    "id": "29"
  },
  {
    "text": "I have a dream that one day this nation will rise up and live out the true meaning of its creed: \\\"We hold these truths to be self-evident, that all men are created equal.\\\"",
    "speaker": "Martin Luther King Jr.",
    "id": "30"
  }
]
